derivflow/__init__.py
derivflow/_version.py
derivflow/calibration/__init__.py
derivflow/core/__init__.py
derivflow/core/pricing_engine.py
derivflow/exotic/__init__.py
derivflow/exotic/asian_options.py
derivflow/exotic/barrier_options.py
derivflow/greeks/__init__.py
derivflow/greeks/calculator.py
derivflow/models/__init__.py
derivflow/models/heston.py
derivflow/portfolio/__init__.py
derivflow/portfolio/portfolio_risk.py
derivflow/utils/__init__.py
derivflow/utils/market_data.py
derivflow/visualization/__init__.py
derivflow/visualization/dashboard.py
derivflow/volatility/__init__.py
derivflow/volatility/surface.py
derivflow_finance-0.1.2.dist-info/licenses/LICENSE
derivflow_finance-0.1.2.dist-info/METADATA
derivflow_finance-0.1.2.dist-info/WHEEL
derivflow_finance-0.1.2.dist-info/entry_points.txt
derivflow_finance-0.1.2.dist-info/top_level.txt
derivflow_finance-0.1.2.dist-info/RECORD
