Metadata-Version: 2.4
Name: derivflow-finance
Version: 0.1.2
Summary: Advanced derivatives analytics platform for quantitative finance
Home-page: https://github.com/jeevanba273/derivflow-finance
Author: Jeevan B A
Author-email: Jeevan B A <jeevanba273@gmail.com>
Maintainer-email: Jeevan B A <jeevanba273@gmail.com>
License: MIT
Project-URL: Homepage, https://github.com/jeevanba273/derivflow-finance
Project-URL: Documentation, https://github.com/jeevanba273/derivflow-finance/wiki
Project-URL: Repository, https://github.com/jeevanba273/derivflow-finance.git
Project-URL: Bug Tracker, https://github.com/jeevanba273/derivflow-finance/issues
Keywords: derivatives,finance,quantitative,options,pricing,risk,analytics,monte-carlo,black-scholes,greeks
Platform: any
Classifier: Development Status :: 4 - Beta
Classifier: Intended Audience :: Financial and Insurance Industry
Classifier: Intended Audience :: Science/Research
Classifier: Intended Audience :: Developers
Classifier: Topic :: Office/Business :: Financial
Classifier: Topic :: Scientific/Engineering :: Mathematics
Classifier: License :: OSI Approved :: MIT License
Classifier: Programming Language :: Python :: 3
Classifier: Programming Language :: Python :: 3.8
Classifier: Programming Language :: Python :: 3.9
Classifier: Programming Language :: Python :: 3.10
Classifier: Programming Language :: Python :: 3.11
Classifier: Programming Language :: Python :: 3.12
Requires-Python: >=3.8
License-File: LICENSE
Requires-Dist: numpy>=1.20.0
Requires-Dist: scipy>=1.7.0
Requires-Dist: pandas>=1.3.0
Requires-Dist: matplotlib>=3.4.0
Requires-Dist: plotly>=5.0.0
Requires-Dist: numba>=0.56.0
Requires-Dist: yfinance>=0.1.70
Requires-Dist: scikit-learn>=1.0.0
Provides-Extra: dev
Requires-Dist: pytest>=6.0; extra == "dev"
Requires-Dist: pytest-cov>=2.0; extra == "dev"
Requires-Dist: black>=21.0; extra == "dev"
Requires-Dist: flake8>=3.9; extra == "dev"
Requires-Dist: mypy>=0.910; extra == "dev"
Requires-Dist: jupyter>=1.0.0; extra == "dev"
Provides-Extra: docs
Requires-Dist: sphinx>=4.0; extra == "docs"
Requires-Dist: sphinx-rtd-theme>=1.0; extra == "docs"
Requires-Dist: myst-parser>=0.15; extra == "docs"
Provides-Extra: visualization
Requires-Dist: plotly>=5.0.0; extra == "visualization"
Requires-Dist: matplotlib>=3.4.0; extra == "visualization"
Requires-Dist: seaborn>=0.11.0; extra == "visualization"
Dynamic: author
Dynamic: home-page
Dynamic: license-file
Dynamic: platform
Dynamic: requires-python
